ssh_stream/__init__.py
ssh_stream/client.py
ssh_stream/server.py
ssh_stream-0.0.3.dist-info/METADATA
ssh_stream-0.0.3.dist-info/WHEEL
ssh_stream-0.0.3.dist-info/licenses/LICENSE
ssh_stream-0.0.3.dist-info/RECORD
